verilog/04-inversor/inv.v
//-- Verilog hello world example
//-  A NOT gate
module inv(input A, output B);
wire A;
wire B;


  assign B = !A;

endmodule

verilog/04-inversor/inv_tb.v
//-- inversor test bench
module inv_tb;

reg clk = 0;
wire B;

inv G1 (
  .A (clk),
  .B (B)
);

initial begin
     $dumpfile("inv_test.vcd");
     $dumpvars(0,inv_tb);

     # 500 $finish;
end

initial begin
  clk = 0;
end

  always #1 clk = !clk;

endmodule

verilog/04-inversor/inv_test.vcd
$date
	Fri Jul 31 08:59:19 2015
$end
$version
	Icarus Verilog
$end
$timescale
	1s
$end
$scope module inv_tb $end
$var wire 1 ! B $end
$var reg 1 " clk $end
$scope module G1 $end
$var wire 1 # A $end
$var wire 1 ! B $end
$upscope $end
$upscope $end
$enddefinitions $end
#0
$dumpvars
0#
0"
1!
$end
#1
1"
1#
0!
#2
0"
0#
1!
#3
1"
1#
0!
#4
0"
0#
1!
#5
1"
1#
0!
#6
0"
0#
1!
#7
1"
1#
0!
#8
0"
0#
1!
#9
1"
1#
0!
#10
0"
0#
1!
#11
1"
1#
0!
#12
0"
0#
1!
#13
1"
1#
0!
#14
0"
0#
1!
#15
1"
1#
0!
#16
0"
0#
1!
#17
1"
1#
0!
#18
0"
0#
1!
#19
1"
1#
0!
#20
0"
0#
1!
#21
1"
1#
0!
#22
0"
0#
1!
#23
1"
1#
0!
#24
0"
0#
1!
#25
1"
1#
0!
#26
0"
0#
1!
#27
1"
1#
0!
#28
0"
0#
1!
#29
1"
1#
0!
#30
0"
0#
1!
#31
1"
1#
0!
#32
0"
0#
1!
#33
1"
1#
0!
#34
0"
0#
1!
#35
1"
1#
0!
#36
0"
0#
1!
#37
1"
1#
0!
#38
0"
0#
1!
#39
1"
1#
0!
#40
0"
0#
1!
#41
1"
1#
0!
#42
0"
0#
1!
#43
1"
1#
0!
#44
0"
0#
1!
#45
1"
1#
0!
#46
0"
0#
1!
#47
1"
1#
0!
#48
0"
0#
1!
#49
1"
1#
0!
#50
0"
0#
1!
#51
1"
1#
0!
#52
0"
0#
1!
#53
1"
1#
0!
#54
0"
0#
1!
#55
1"
1#
0!
#56
0"
0#
1!
#57
1"
1#
0!
#58
0"
0#
1!
#59
1"
1#
0!
#60
0"
0#
1!
#61
1"
1#
0!
#62
0"
0#
1!
#63
1"
1#
0!
#64
0"
0#
1!
#65
1"
1#
0!
#66
0"
0#
1!
#67
1"
1#
0!
#68
0"
0#
1!
#69
1"
1#
0!
#70
0"
0#
1!
#71
1"
1#
0!
#72
0"
0#
1!
#73
1"
1#
0!
#74
0"
0#
1!
#75
1"
1#
0!
#76
0"
0#
1!
#77
1"
1#
0!
#78
0"
0#
1!
#79
1"
1#
0!
#80
0"
0#
1!
#81
1"
1#
0!
#82
0"
0#
1!
#83
1"
1#
0!
#84
0"
0#
1!
#85
1"
1#
0!
#86
0"
0#
1!
#87
1"
1#
0!
#88
0"
0#
1!
#89
1"
1#
0!
#90
0"
0#
1!
#91
1"
1#
0!
#92
0"
0#
1!
#93
1"
1#
0!
#94
0"
0#
1!
#95
1"
1#
0!
#96
0"
0#
1!
#97
1"
1#
0!
#98
0"
0#
1!
#99
1"
1#
0!
#100
0"
0#
1!
#101
1"
1#
0!
#102
0"
0#
1!
#103
1"
1#
0!
#104
0"
0#
1!
#105
1"
1#
0!
#106
0"
0#
1!
#107
1"
1#
0!
#108
0"
0#
1!
#109
1"
1#
0!
#110
0"
0#
1!
#111
1"
1#
0!
#112
0"
0#
1!
#113
1"
1#
0!
#114
0"
0#
1!
#115
1"
1#
0!
#116
0"
0#
1!
#117
1"
1#
0!
#118
0"
0#
1!
#119
1"
1#
0!
#120
0"
0#
1!
#121
1"
1#
0!
#122
0"
0#
1!
#123
1"
1#
0!
#124
0"
0#
1!
#125
1"
1#
0!
#126
0"
0#
1!
#127
1"
1#
0!
#128
0"
0#
1!
#129
1"
1#
0!
#130
0"
0#
1!
#131
1"
1#
0!
#132
0"
0#
1!
#133
1"
1#
0!
#134
0"
0#
1!
#135
1"
1#
0!
#136
0"
0#
1!
#137
1"
1#
0!
#138
0"
0#
1!
#139
1"
1#
0!
#140
0"
0#
1!
#141
1"
1#
0!
#142
0"
0#
1!
#143
1"
1#
0!
#144
0"
0#
1!
#145
1"
1#
0!
#146
0"
0#
1!
#147
1"
1#
0!
#148
0"
0#
1!
#149
1"
1#
0!
#150
0"
0#
1!
#151
1"
1#
0!
#152
0"
0#
1!
#153
1"
1#
0!
#154
0"
0#
1!
#155
1"
1#
0!
#156
0"
0#
1!
#157
1"
1#
0!
#158
0"
0#
1!
#159
1"
1#
0!
#160
0"
0#
1!
#161
1"
1#
0!
#162
0"
0#
1!
#163
1"
1#
0!
#164
0"
0#
1!
#165
1"
1#
0!
#166
0"
0#
1!
#167
1"
1#
0!
#168
0"
0#
1!
#169
1"
1#
0!
#170
0"
0#
1!
#171
1"
1#
0!
#172
0"
0#
1!
#173
1"
1#
0!
#174
0"
0#
1!
#175
1"
1#
0!
#176
0"
0#
1!
#177
1"
1#
0!
#178
0"
0#
1!
#179
1"
1#
0!
#180
0"
0#
1!
#181
1"
1#
0!
#182
0"
0#
1!
#183
1"
1#
0!
#184
0"
0#
1!
#185
1"
1#
0!
#186
0"
0#
1!
#187
1"
1#
0!
#188
0"
0#
1!
#189
1"
1#
0!
#190
0"
0#
1!
#191
1"
1#
0!
#192
0"
0#
1!
#193
1"
1#
0!
#194
0"
0#
1!
#195
1"
1#
0!
#196
0"
0#
1!
#197
1"
1#
0!
#198
0"
0#
1!
#199
1"
1#
0!
#200
0"
0#
1!
#201
1"
1#
0!
#202
0"
0#
1!
#203
1"
1#
0!
#204
0"
0#
1!
#205
1"
1#
0!
#206
0"
0#
1!
#207
1"
1#
0!
#208
0"
0#
1!
#209
1"
1#
0!
#210
0"
0#
1!
#211
1"
1#
0!
#212
0"
0#
1!
#213
1"
1#
0!
#214
0"
0#
1!
#215
1"
1#
0!
#216
0"
0#
1!
#217
1"
1#
0!
#218
0"
0#
1!
#219
1"
1#
0!
#220
0"
0#
1!
#221
1"
1#
0!
#222
0"
0#
1!
#223
1"
1#
0!
#224
0"
0#
1!
#225
1"
1#
0!
#226
0"
0#
1!
#227
1"
1#
0!
#228
0"
0#
1!
#229
1"
1#
0!
#230
0"
0#
1!
#231
1"
1#
0!
#232
0"
0#
1!
#233
1"
1#
0!
#234
0"
0#
1!
#235
1"
1#
0!
#236
0"
0#
1!
#237
1"
1#
0!
#238
0"
0#
1!
#239
1"
1#
0!
#240
0"
0#
1!
#241
1"
1#
0!
#242
0"
0#
1!
#243
1"
1#
0!
#244
0"
0#
1!
#245
1"
1#
0!
#246
0"
0#
1!
#247
1"
1#
0!
#248
0"
0#
1!
#249
1"
1#
0!
#250
0"
0#
1!
#251
1"
1#
0!
#252
0"
0#
1!
#253
1"
1#
0!
#254
0"
0#
1!
#255
1"
1#
0!
#256
0"
0#
1!
#257
1"
1#
0!
#258
0"
0#
1!
#259
1"
1#
0!
#260
0"
0#
1!
#261
1"
1#
0!
#262
0"
0#
1!
#263
1"
1#
0!
#264
0"
0#
1!
#265
1"
1#
0!
#266
0"
0#
1!
#267
1"
1#
0!
#268
0"
0#
1!
#269
1"
1#
0!
#270
0"
0#
1!
#271
1"
1#
0!
#272
0"
0#
1!
#273
1"
1#
0!
#274
0"
0#
1!
#275
1"
1#
0!
#276
0"
0#
1!
#277
1"
1#
0!
#278
0"
0#
1!
#279
1"
1#
0!
#280
0"
0#
1!
#281
1"
1#
0!
#282
0"
0#
1!
#283
1"
1#
0!
#284
0"
0#
1!
#285
1"
1#
0!
#286
0"
0#
1!
#287
1"
1#
0!
#288
0"
0#
1!
#289
1"
1#
0!
#290
0"
0#
1!
#291
1"
1#
0!
#292
0"
0#
1!
#293
1"
1#
0!
#294
0"
0#
1!
#295
1"
1#
0!
#296
0"
0#
1!
#297
1"
1#
0!
#298
0"
0#
1!
#299
1"
1#
0!
#300
0"
0#
1!
#301
1"
1#
0!
#302
0"
0#
1!
#303
1"
1#
0!
#304
0"
0#
1!
#305
1"
1#
0!
#306
0"
0#
1!
#307
1"
1#
0!
#308
0"
0#
1!
#309
1"
1#
0!
#310
0"
0#
1!
#311
1"
1#
0!
#312
0"
0#
1!
#313
1"
1#
0!
#314
0"
0#
1!
#315
1"
1#
0!
#316
0"
0#
1!
#317
1"
1#
0!
#318
0"
0#
1!
#319
1"
1#
0!
#320
0"
0#
1!
#321
1"
1#
0!
#322
0"
0#
1!
#323
1"
1#
0!
#324
0"
0#
1!
#325
1"
1#
0!
#326
0"
0#
1!
#327
1"
1#
0!
#328
0"
0#
1!
#329
1"
1#
0!
#330
0"
0#
1!
#331
1"
1#
0!
#332
0"
0#
1!
#333
1"
1#
0!
#334
0"
0#
1!
#335
1"
1#
0!
#336
0"
0#
1!
#337
1"
1#
0!
#338
0"
0#
1!
#339
1"
1#
0!
#340
0"
0#
1!
#341
1"
1#
0!
#342
0"
0#
1!
#343
1"
1#
0!
#344
0"
0#
1!
#345
1"
1#
0!
#346
0"
0#
1!
#347
1"
1#
0!
#348
0"
0#
1!
#349
1"
1#
0!
#350
0"
0#
1!
#351
1"
1#
0!
#352
0"
0#
1!
#353
1"
1#
0!
#354
0"
0#
1!
#355
1"
1#
0!
#356
0"
0#
1!
#357
1"
1#
0!
#358
0"
0#
1!
#359
1"
1#
0!
#360
0"
0#
1!
#361
1"
1#
0!
#362
0"
0#
1!
#363
1"
1#
0!
#364
0"
0#
1!
#365
1"
1#
0!
#366
0"
0#
1!
#367
1"
1#
0!
#368
0"
0#
1!
#369
1"
1#
0!
#370
0"
0#
1!
#371
1"
1#
0!
#372
0"
0#
1!
#373
1"
1#
0!
#374
0"
0#
1!
#375
1"
1#
0!
#376
0"
0#
1!
#377
1"
1#
0!
#378
0"
0#
1!
#379
1"
1#
0!
#380
0"
0#
1!
#381
1"
1#
0!
#382
0"
0#
1!
#383
1"
1#
0!
#384
0"
0#
1!
#385
1"
1#
0!
#386
0"
0#
1!
#387
1"
1#
0!
#388
0"
0#
1!
#389
1"
1#
0!
#390
0"
0#
1!
#391
1"
1#
0!
#392
0"
0#
1!
#393
1"
1#
0!
#394
0"
0#
1!
#395
1"
1#
0!
#396
0"
0#
1!
#397
1"
1#
0!
#398
0"
0#
1!
#399
1"
1#
0!
#400
0"
0#
1!
#401
1"
1#
0!
#402
0"
0#
1!
#403
1"
1#
0!
#404
0"
0#
1!
#405
1"
1#
0!
#406
0"
0#
1!
#407
1"
1#
0!
#408
0"
0#
1!
#409
1"
1#
0!
#410
0"
0#
1!
#411
1"
1#
0!
#412
0"
0#
1!
#413
1"
1#
0!
#414
0"
0#
1!
#415
1"
1#
0!
#416
0"
0#
1!
#417
1"
1#
0!
#418
0"
0#
1!
#419
1"
1#
0!
#420
0"
0#
1!
#421
1"
1#
0!
#422
0"
0#
1!
#423
1"
1#
0!
#424
0"
0#
1!
#425
1"
1#
0!
#426
0"
0#
1!
#427
1"
1#
0!
#428
0"
0#
1!
#429
1"
1#
0!
#430
0"
0#
1!
#431
1"
1#
0!
#432
0"
0#
1!
#433
1"
1#
0!
#434
0"
0#
1!
#435
1"
1#
0!
#436
0"
0#
1!
#437
1"
1#
0!
#438
0"
0#
1!
#439
1"
1#
0!
#440
0"
0#
1!
#441
1"
1#
0!
#442
0"
0#
1!
#443
1"
1#
0!
#444
0"
0#
1!
#445
1"
1#
0!
#446
0"
0#
1!
#447
1"
1#
0!
#448
0"
0#
1!
#449
1"
1#
0!
#450
0"
0#
1!
#451
1"
1#
0!
#452
0"
0#
1!
#453
1"
1#
0!
#454
0"
0#
1!
#455
1"
1#
0!
#456
0"
0#
1!
#457
1"
1#
0!
#458
0"
0#
1!
#459
1"
1#
0!
#460
0"
0#
1!
#461
1"
1#
0!
#462
0"
0#
1!
#463
1"
1#
0!
#464
0"
0#
1!
#465
1"
1#
0!
#466
0"
0#
1!
#467
1"
1#
0!
#468
0"
0#
1!
#469
1"
1#
0!
#470
0"
0#
1!
#471
1"
1#
0!
#472
0"
0#
1!
#473
1"
1#
0!
#474
0"
0#
1!
#475
1"
1#
0!
#476
0"
0#
1!
#477
1"
1#
0!
#478
0"
0#
1!
#479
1"
1#
0!
#480
0"
0#
1!
#481
1"
1#
0!
#482
0"
0#
1!
#483
1"
1#
0!
#484
0"
0#
1!
#485
1"
1#
0!
#486
0"
0#
1!
#487
1"
1#
0!
#488
0"
0#
1!
#489
1"
1#
0!
#490
0"
0#
1!
#491
1"
1#
0!
#492
0"
0#
1!
#493
1"
1#
0!
#494
0"
0#
1!
#495
1"
1#
0!
#496
0"
0#
1!
#497
1"
1#
0!
#498
0"
0#
1!
#499
1"
1#
0!
#500
0"
0#
1!
